cythonimagever/LICENSE.txt
cythonimagever/README.MD
cythonimagever/__init__.py
cythonimagever/cyimage.pyx
cythonimagever/cyimage_compile.py
cythonimagever/requirements.txt
cythonimagever/thirdparty.json
cythonimagever-0.10.dist-info/LICENSE.rst
cythonimagever-0.10.dist-info/METADATA
cythonimagever-0.10.dist-info/WHEEL
cythonimagever-0.10.dist-info/top_level.txt
cythonimagever-0.10.dist-info/RECORD
